clioetxt/__init__.py
clioetxt/load_txt.py
clioetxt/merge.py
clioetxt/transform.py
clioetxt-2.3.dist-info/LICENSE
clioetxt-2.3.dist-info/METADATA
clioetxt-2.3.dist-info/WHEEL
clioetxt-2.3.dist-info/top_level.txt
clioetxt-2.3.dist-info/RECORD
