Metadata-Version: 2.1
Name: clioetxt
Version: 2.3
Summary: A module to extract, transform (search, invert, format) and load text file or csv file
Home-page: UNKNOWN
Author: Cheny Lioe
Author-email: chenylioe@yahoo.com
License: UNKNOWN
Keywords: txt file,csv file
Platform: UNKNOWN
License-File: LICENSE
